genp/__init__.py
genp-0.2.dist-info/METADATA
genp-0.2.dist-info/WHEEL
genp-0.2.dist-info/top_level.txt
genp-0.2.dist-info/RECORD
