Metadata-Version: 2.1
Name: genp
Version: 0.2
Summary: This is simple python password generation lib.
Home-page: https://github.com/IvanIsak2000/password_generation_lib
Author: VANECK
Author-email: vingving648@gmail.com
License: UNKNOWN
Platform: UNKNOWN
Classifier: Programming Language :: Python :: 3
Classifier: License :: OSI Approved :: MIT License
Classifier: Operating System :: OS Independent
Requires-Python: >=3.6
